Metadata-Version: 2.1
Name: boptools
Version: 0.12
Summary: Brown Opinion Project utilities.
Home-page: https://github.com/brownopinionproject/boptools/tree/main
Author: Arjun Shanmugam
Author-email: arjun_shanmugam@brown.edu
License: MIT
Platform: UNKNOWN
License-File: LICENSE
